pyfindr/__init__.py
pyfindr/__main__.py
pyfindr/cli.py
pyfindr/consts.py
pyfindr/search.py
pyfindr-1.0.2.dist-info/entry_points.txt
pyfindr-1.0.2.dist-info/LICENSE
pyfindr-1.0.2.dist-info/METADATA
pyfindr-1.0.2.dist-info/WHEEL
pyfindr-1.0.2.dist-info/RECORD
