Metadata-Version: 2.1
Name: pyfindr
Version: 1.0.2
Summary: Recursively search files
Home-page: https://github.com/YisusChrist/findr
License: GPL-2.0-only
Author: Julio Cabria
Author-email: juliocabria@tutanota.com
Requires-Python: >=3.8,<4.0
Classifier: License :: OSI Approved :: GNU General Public License v2 (GPLv2)
Classifier: Programming Language :: Python :: 3
Classifier: Programming Language :: Python :: 3.8
Classifier: Programming Language :: Python :: 3.9
Classifier: Programming Language :: Python :: 3.10
Classifier: Programming Language :: Python :: 3.11
Classifier: Programming Language :: Python :: 3.12
Requires-Dist: rich (>=13.7.1,<14.0.0)
Project-URL: Repository, https://github.com/YisusChrist/findr
